opendorslib/__init__.py
opendorslib/abc.py
opendorslib/extract_urls.py
opendorslib/joss.py
opendorslib/logging.py
opendorslib/mention_metadata/__init__.py
opendorslib/mention_metadata/arxiv.py
opendorslib/mention_metadata/pmc.py
opendorslib/merge/__init__.py
opendorslib/merge/merge.py
opendorslib/metadata.py
opendorslib/urls.py
opendorslib-0.1.dev86.dist-info/LICENSES/CC-BY-4.0.txt
opendorslib-0.1.dev86.dist-info/LICENSES/CC0-1.0.txt
opendorslib-0.1.dev86.dist-info/LICENSES/MIT.txt
opendorslib-0.1.dev86.dist-info/METADATA
opendorslib-0.1.dev86.dist-info/WHEEL
opendorslib-0.1.dev86.dist-info/RECORD
