Metadata-Version: 2.1
Name: opendorslib
Version: 0.1.dev86
Summary: Library for creating the OpenDORS dataset.
License: MIT
Author: Druskat, Stephan
Author-email: stephan.druskat@dlr.de
Maintainer: Druskat, Stephan
Maintainer-email: stephan.druskat@dlr.de
Requires-Python: >=3.11,<4.0
Classifier: Development Status :: 1 - Planning
Classifier: License :: OSI Approved :: MIT License
Classifier: Programming Language :: Python :: 3
Classifier: Programming Language :: Python :: 3.11
Classifier: Programming Language :: Python :: 3.12
Requires-Dist: jsonpath-ng (>=1.5.3,<2.0.0)
Requires-Dist: pydantic (>=2.0,<3.0)
Requires-Dist: ratelimit (>=2.2.1,<3.0.0)
Requires-Dist: urllib3 (>=2.0.7,<3.0.0)
Requires-Dist: xmltodict (>=0.13.0,<0.14.0)
